deckhouse/__init__.py
deckhouse/conversions.py
deckhouse/hook.py
deckhouse/kubernetes.py
deckhouse/metrics.py
deckhouse/module.py
deckhouse/storage.py
deckhouse/tests.py
deckhouse/utils.py
deckhouse/validations.py
deckhouse/values.py
deckhouse-0.4.11.dist-info/LICENSE
deckhouse-0.4.11.dist-info/METADATA
deckhouse-0.4.11.dist-info/WHEEL
deckhouse-0.4.11.dist-info/RECORD
