Metadata-Version: 2.1
Name: deckhouse
Version: 0.4.11
Summary: Wrapper for hooks for Deckhouse, Addon Operator, and Shell Operator by Flant
License: Apache-2.0
Author: Eugene Shevchenko
Author-email: evgeny.shevchenko@flant.com
Requires-Python: >=3.8,<4.0
Classifier: License :: OSI Approved :: Apache Software License
Classifier: Programming Language :: Python :: 3
Classifier: Programming Language :: Python :: 3.8
Classifier: Programming Language :: Python :: 3.9
Classifier: Programming Language :: Python :: 3.10
Classifier: Programming Language :: Python :: 3.11
Requires-Dist: dictdiffer (>=0.9.0,<0.10.0)
